sapo/__init__.py
sapo/parquet_validator.py
sapo/schema_fetcher.py
sapo/sqlite_helpers.py
sapo/sqlite_schema_to_yaml.py
sapo/sqlite_validator.py
sapo-0.2.0.dist-info/WHEEL
sapo-0.2.0.dist-info/METADATA
sapo-0.2.0.dist-info/RECORD
