Metadata-Version: 2.1
Name: sapo
Version: 0.2.0
Summary: 
Author: MrPowers
Author-email: matthewkevinpowers@gmail.com
Requires-Python: >=3.7,<4.0
Classifier: Programming Language :: Python :: 3
Classifier: Programming Language :: Python :: 3.7
Classifier: Programming Language :: Python :: 3.8
Requires-Dist: pyarrow (>=1.0.1,<2.0.0)
Requires-Dist: pyyaml (>=5.3.1,<6.0.0)
